cockroachdb/__init__.py
cockroachdb/sqlalchemy/__init__.py
cockroachdb/sqlalchemy/dialect.py
cockroachdb/sqlalchemy/stmt_compiler.py
cockroachdb/sqlalchemy/test_requirements.py
cockroachdb/sqlalchemy/transaction.py
cockroachdb-0.3.5.dist-info/LICENSE
cockroachdb-0.3.5.dist-info/METADATA
cockroachdb-0.3.5.dist-info/WHEEL
cockroachdb-0.3.5.dist-info/entry_points.txt
cockroachdb-0.3.5.dist-info/top_level.txt
cockroachdb-0.3.5.dist-info/RECORD
